vishesh/__init__.py
vishesh/api_handler.py
vishesh/file_manager.py
vishesh/main.py
vishesh/setup_dependencies.py
vishesh_helloworld/__init__.py
vishesh_helloworld/main.py
vishesh-0.4.dist-info/METADATA
vishesh-0.4.dist-info/WHEEL
vishesh-0.4.dist-info/entry_points.txt
vishesh-0.4.dist-info/top_level.txt
vishesh-0.4.dist-info/RECORD
