Metadata-Version: 2.2
Name: vishesh
Version: 0.4
Summary: LeetCode Problem Helper Tool
Home-page: https://github.com/visheshj2005/leetcode
Author: Vishesh Jain
Author-email: visheshj2005@gmail.com
Classifier: Programming Language :: Python :: 3
Classifier: License :: OSI Approved :: MIT License
Classifier: Operating System :: OS Independent
Requires-Python: >=3.6
Requires-Dist: requests
Dynamic: author
Dynamic: author-email
Dynamic: classifier
Dynamic: home-page
Dynamic: requires-dist
Dynamic: requires-python
Dynamic: summary
